rubix/__init__.py
rubix/agent/__init__.py
rubix/agent/dna/__init__.py
rubix/agent/dna/handler.py
rubix/agent/dna/node_client.py
rubix/agent/dna/token.txt
rubix/agent/dna/trust.py
rubix_agent_dna-0.1.17.dist-info/METADATA
rubix_agent_dna-0.1.17.dist-info/WHEEL
rubix_agent_dna-0.1.17.dist-info/top_level.txt
rubix_agent_dna-0.1.17.dist-info/RECORD
