Metadata-Version: 2.4
Name: rubix.agent.dna
Version: 0.1.17
Summary: Rubix agent DNA: trust + node client + handler utilities
Author-email: Your Name <you@example.com>
License: MIT
Requires-Python: >=3.11
Requires-Dist: requests>=2.0.0
Requires-Dist: python-dotenv>=1.0.0
Requires-Dist: rubix-py
